fplore/fast_util.cpython-38-x86_64-linux-gnu.so
fplore/util.py
fplore/arpes.py
fplore/run.py
fplore/plot.py
fplore/__init__.py
fplore/logging.py
fplore/files/config.py
fplore/files/misc.py
fplore/files/dos.py
fplore/files/band.py
fplore/files/base.py
fplore/files/__init__.py
fplore.libs/libgomp-a34b3233.so.1.0.0
fplore-0.6.dist-info/METADATA
fplore-0.6.dist-info/top_level.txt
fplore-0.6.dist-info/WHEEL
fplore-0.6.dist-info/RECORD
fplore-0.6.dist-info/LICENSE
