Metadata-Version: 2.1
Name: fplore
Version: 0.6
Summary: FPLO run evaluation
License: GPLv3
Project-URL: Homepage, https://github.com/mueslo/fplore
Keywords: dft,fplo,physics,chemistry
Classifier: Operating System :: OS Independent
Classifier: Programming Language :: Python
Classifier: Programming Language :: Python :: 3
Classifier: Programming Language :: Python :: 3.8
Classifier: Programming Language :: Python :: 3.9
Classifier: Programming Language :: Python :: 3.10
Classifier: Programming Language :: Python :: 3.11
Classifier: Programming Language :: Python :: 3.12
Classifier: License :: OSI Approved :: GNU General Public License v3 (GPLv3)
Classifier: Intended Audience :: Science/Research
Classifier: Topic :: Scientific/Engineering :: Physics
Classifier: Topic :: Scientific/Engineering :: Chemistry
Requires-Python: <4,>=3.8
License-File: LICENSE
Requires-Dist: numpy~=1.21
Requires-Dist: scipy~=1.7
Requires-Dist: pymatgen~=2022.5.19
Requires-Dist: orderedattrdict~=1.5
Requires-Dist: logbook~=1.5
Requires-Dist: pyparsing~=3.0
Requires-Dist: progressbar2~=3.38
Requires-Dist: matplotlib~=3.4
Provides-Extra: tests
Requires-Dist: tox; extra == "tests"
Provides-Extra: tests-core
Requires-Dist: pytest~=7.4; extra == "tests-core"
Requires-Dist: pytest-cases; extra == "tests-core"
Requires-Dist: pytest-logbook; extra == "tests-core"
Provides-Extra: docs
Requires-Dist: sphinx~=7.0; extra == "docs"
Requires-Dist: sphinx-gallery~=0.13; extra == "docs"
Requires-Dist: Pillow; extra == "docs"
